ctm/__init__.py
ctm/ctm.py
ctm/ctm_rsd.py
ctm/cosmology/__init__.py
ctm/cosmology/cosmology.py
ctm/cosmology/time_dependence.py
ctm/misc/__init__.py
ctm/misc/plotting.py
ctm/misc/progress_update.py
ctm/misc/timer.py
ctm/power_spectrum/LPT.py
ctm/power_spectrum/LPT_oneloop.py
ctm/power_spectrum/__init__.py
ctm/power_spectrum/correlation_funcs.py
ctm/power_spectrum/covariances.py
ctm/power_spectrum/covariances_oneloop.py
ctm/power_spectrum/ctm_power.py
ctm/power_spectrum/integration.py
ctm/power_spectrum/integration_rsd.py
ctmmodule-1.12.dist-info/METADATA
ctmmodule-1.12.dist-info/WHEEL
ctmmodule-1.12.dist-info/top_level.txt
ctmmodule-1.12.dist-info/RECORD
